COPYING
MANIFEST.in
README.md
setup.py
/home/meh/devel/hotdoc/cmark/extensions/core-extensions.c
/home/meh/devel/hotdoc/cmark/extensions/ext_scanners.c
/home/meh/devel/hotdoc/cmark/src/blocks.c
/home/meh/devel/hotdoc/cmark/src/buffer.c
/home/meh/devel/hotdoc/cmark/src/cmark.c
/home/meh/devel/hotdoc/cmark/src/cmark_ctype.c
/home/meh/devel/hotdoc/cmark/src/commonmark.c
/home/meh/devel/hotdoc/cmark/src/houdini_href_e.c
/home/meh/devel/hotdoc/cmark/src/houdini_html_e.c
/home/meh/devel/hotdoc/cmark/src/houdini_html_u.c
/home/meh/devel/hotdoc/cmark/src/html.c
/home/meh/devel/hotdoc/cmark/src/inlines.c
/home/meh/devel/hotdoc/cmark/src/iterator.c
/home/meh/devel/hotdoc/cmark/src/latex.c
/home/meh/devel/hotdoc/cmark/src/linked_list.c
/home/meh/devel/hotdoc/cmark/src/main.c
/home/meh/devel/hotdoc/cmark/src/man.c
/home/meh/devel/hotdoc/cmark/src/node.c
/home/meh/devel/hotdoc/cmark/src/plugin.c
/home/meh/devel/hotdoc/cmark/src/references.c
/home/meh/devel/hotdoc/cmark/src/registry.c
/home/meh/devel/hotdoc/cmark/src/render.c
/home/meh/devel/hotdoc/cmark/src/scanners.c
/home/meh/devel/hotdoc/cmark/src/syntax_extension.c
/home/meh/devel/hotdoc/cmark/src/utf8.c
/home/meh/devel/hotdoc/cmark/src/xml.c
/home/meh/devel/hotdoc/hotdoc/parsers/c_comment_scanner/scanner.c
cmark/.editorconfig
cmark/.git
cmark/.gitignore
cmark/.travis.yml
cmark/CMakeLists.txt
cmark/COPYING
cmark/FindAsan.cmake
cmark/Makefile
cmark/Makefile.nmake
cmark/README.md
cmark/appveyor.yml
cmark/benchmarks.md
cmark/changelog.txt
cmark/nmake.bat
cmark/toolchain-mingw32.cmake
cmark/why-cmark-and-not-x.md
cmark/api_test/CMakeLists.txt
cmark/api_test/cplusplus.cpp
cmark/api_test/cplusplus.h
cmark/api_test/harness.c
cmark/api_test/harness.h
cmark/api_test/main.c
cmark/bench/statistics.py
cmark/bench/stats.py
cmark/bench/samples/block-bq-flat.md
cmark/bench/samples/block-bq-nested.md
cmark/bench/samples/block-code.md
cmark/bench/samples/block-fences.md
cmark/bench/samples/block-heading.md
cmark/bench/samples/block-hr.md
hotdoc.egg-info/PKG-INFO
hotdoc.egg-info/SOURCES.txt
hotdoc.egg-info/dependency_links.txt
hotdoc.egg-info/entry_points.txt
hotdoc.egg-info/requires.txt
hotdoc.egg-info/top_level.txt
